{"stats":{"minecraft:mined":{"minecraft:grass":4,"minecraft:tall_grass":1,"minecraft:grass_block":1,"minecraft:sunflower":1},"minecraft:custom":{"minecraft:jump":206,"minecraft:time_since_rest":19541,"minecraft:damage_taken":60,"minecraft:damage_dealt":162,"minecraft:leave_game":3,"minecraft:sprint_one_cm":16602,"minecraft:play_time":19541,"minecraft:time_since_death":19541,"minecraft:walk_on_water_one_cm":1237,"minecraft:walk_one_cm":4903,"minecraft:total_world_time":19541,"minecraft:walk_under_water_one_cm":415,"minecraft:swim_one_cm":1564,"minecraft:fall_one_cm":4815,"minecraft:fly_one_cm":64826},"minecraft:picked_up":{"minecraft:dirt":1}},"DataVersion":3465}